nxp_pp/__init__.py
nxp_pp-0.2.0.dist-info/METADATA
nxp_pp-0.2.0.dist-info/WHEEL
nxp_pp-0.2.0.dist-info/entry_points.txt
nxp_pp-0.2.0.dist-info/top_level.txt
nxp_pp-0.2.0.dist-info/RECORD
